fast_langgraph-0.1.12.dist-info/METADATA
fast_langgraph-0.1.12.dist-info/WHEEL
fast_langgraph-0.1.12.dist-info/licenses/LICENSE
fast_langgraph.libs/libgcc_s-6d2d9dc8.so.1
fast_langgraph/__init__.py
fast_langgraph/accelerator.py
fast_langgraph/algo_shims.py
fast_langgraph/cache_decorator.py
fast_langgraph/checkpoint_wrapper.py
fast_langgraph/executor_cache.py
fast_langgraph/fast_langgraph.abi3.so
fast_langgraph/optimizations.py
fast_langgraph/profiler.py
fast_langgraph/py.typed
fast_langgraph/shim.py
fast_langgraph-0.1.12.dist-info/RECORD
