Metadata-Version: 2.4
Name: fast-langgraph
Version: 0.1.12
Classifier: Development Status :: 4 - Beta
Classifier: Intended Audience :: Developers
Classifier: License :: OSI Approved :: MIT License
Classifier: Programming Language :: Python :: 3
Classifier: Programming Language :: Python :: 3.9
Classifier: Programming Language :: Python :: 3.10
Classifier: Programming Language :: Python :: 3.11
Classifier: Programming Language :: Python :: 3.12
Classifier: Programming Language :: Python :: 3.13
Classifier: Programming Language :: Rust
Classifier: Operating System :: OS Independent
Classifier: Topic :: Software Development :: Libraries :: Python Modules
Classifier: Topic :: Scientific/Engineering :: Artificial Intelligence
Requires-Dist: typing-extensions>=4.8.0
Requires-Dist: pytest>=7.4.0 ; extra == 'dev'
Requires-Dist: pytest-cov>=4.1.0 ; extra == 'dev'
Requires-Dist: pytest-benchmark>=4.0.0 ; extra == 'dev'
Requires-Dist: pytest-asyncio>=0.21.0 ; extra == 'dev'
Requires-Dist: black>=23.0.0 ; extra == 'dev'
Requires-Dist: isort>=5.12.0 ; extra == 'dev'
Requires-Dist: mypy>=1.5.0 ; extra == 'dev'
Requires-Dist: ruff>=0.1.0 ; extra == 'dev'
Requires-Dist: maturin>=1.3.0 ; extra == 'dev'
Requires-Dist: mkdocs>=1.5.0 ; extra == 'docs'
Requires-Dist: mkdocs-material>=9.5.0 ; extra == 'docs'
Requires-Dist: mkdocs-autorefs>=0.5.0 ; extra == 'docs'
Requires-Dist: pymdown-extensions>=10.0 ; extra == 'docs'
Requires-Dist: langgraph>=0.1.0 ; extra == 'test'
Requires-Dist: langgraph>=0.1.0 ; extra == 'integration'
Requires-Dist: langchain-core>=0.2.0 ; extra == 'integration'
Requires-Dist: httpx>=0.25.0 ; extra == 'integration'
Provides-Extra: dev
Provides-Extra: docs
Provides-Extra: test
Provides-Extra: integration
License-File: LICENSE
Summary: High-performance Rust implementation of LangGraph components
Keywords: langgraph,rust,performance,graph,ai,fast
Home-Page: https://github.com/langchain-ai/langgraph
Author-email: Neul Labs <hello@neul.ai>
License: MIT
Requires-Python: >=3.9
Project-URL: Homepage, https://github.com/neul-labs/fast-langgraph
Project-URL: Repository, https://github.com/neul-labs/fast-langgraph
Project-URL: Documentation, https://github.com/neul-labs/fast-langgraph/tree/main/docs
